ironic_tempest_plugin/README.rst
ironic_tempest_plugin/__init__.py
ironic_tempest_plugin/clients.py
ironic_tempest_plugin/config.py
ironic_tempest_plugin/exceptions.py
ironic_tempest_plugin/manager.py
ironic_tempest_plugin/plugin.py
ironic_tempest_plugin/common/__init__.py
ironic_tempest_plugin/common/utils.py
ironic_tempest_plugin/common/waiters.py
ironic_tempest_plugin/rules/basic_ops_rule.json
ironic_tempest_plugin/services/__init__.py
ironic_tempest_plugin/services/introspection_client.py
ironic_tempest_plugin/services/baremetal/__init__.py
ironic_tempest_plugin/services/baremetal/base.py
ironic_tempest_plugin/services/baremetal/v1/__init__.py
ironic_tempest_plugin/services/baremetal/v1/json/__init__.py
ironic_tempest_plugin/services/baremetal/v1/json/baremetal_client.py
ironic_tempest_plugin/tests/__init__.py
ironic_tempest_plugin/tests/api/__init__.py
ironic_tempest_plugin/tests/api/base.py
ironic_tempest_plugin/tests/api/admin/__init__.py
ironic_tempest_plugin/tests/api/admin/api_microversion_fixture.py
ironic_tempest_plugin/tests/api/admin/test_allocations.py
ironic_tempest_plugin/tests/api/admin/test_api_discovery.py
ironic_tempest_plugin/tests/api/admin/test_chassis.py
ironic_tempest_plugin/tests/api/admin/test_conductor.py
ironic_tempest_plugin/tests/api/admin/test_deploy_templates.py
ironic_tempest_plugin/tests/api/admin/test_drivers.py
ironic_tempest_plugin/tests/api/admin/test_inspection_rules.py
ironic_tempest_plugin/tests/api/admin/test_inspection_rules_negatives.py
ironic_tempest_plugin/tests/api/admin/test_microversion_enforcement.py
ironic_tempest_plugin/tests/api/admin/test_nodes.py
ironic_tempest_plugin/tests/api/admin/test_nodestates.py
ironic_tempest_plugin/tests/api/admin/test_portgroups.py
ironic_tempest_plugin/tests/api/admin/test_ports.py
ironic_tempest_plugin/tests/api/admin/test_ports_negative.py
ironic_tempest_plugin/tests/api/admin/test_runbooks.py
ironic_tempest_plugin/tests/api/admin/test_shards.py
ironic_tempest_plugin-2.16.0.dist-info/AUTHORS
ironic_tempest_plugin-2.16.0.dist-info/LICENSE
ironic_tempest_plugin-2.16.0.dist-info/METADATA
ironic_tempest_plugin-2.16.0.dist-info/WHEEL
ironic_tempest_plugin-2.16.0.dist-info/entry_points.txt
ironic_tempest_plugin-2.16.0.dist-info/pbr.json
ironic_tempest_plugin-2.16.0.dist-info/top_level.txt
ironic_tempest_plugin-2.16.0.dist-info/RECORD
